Workbook

Sheet README
A1: Bank to Wealth: Mass-Affluent to HNI Migration Funnel — Wealth-Tier Segmentation Model
A4: PURPOSE
A5: This model simulates how a retail bank (case study: HDFC Bank-style wealth tiers) identifies which of its existing retail customers should be migrated into wealth management / priority banking coverage — the critical first stage of the Bank-to-Wealth cross-sell funnel.
A7: HOW TO USE THIS WORKBOOK
A8: 1. Tier_Criteria (yellow cells) — the scoring weights and benchmarks. Change these to run new scenarios.
A9: 2. Customer_Data — 80 synthetic retail customers with banking behaviour signals (proxy for a bank's CRM extract).
A10: 3. Segmentation_Model — computes a 0-100 Wealth Score per customer and assigns a tier automatically.
A11: 4. Dashboard — tier distribution, AUM concentration, and cross-sell priority flags for the RM handoff.
A13: METHODOLOGY NOTE
A14: Real banks (HDFC Imperia, ICICI Private Banking, Kotak Privy League, Axis Burgundy) use proprietary scoring combining AUM, relationship value, and product depth. This model replicates that logic using five publicly reasoned signals: Average Monthly Balance, Annual Income (via salary credits), Product Holding Breadth, Digital Engagement, and Credit Card Spend. Weights and benchmarks are stated assumptions (yellow cells), documented so they can be defended or adjusted in an interview.
A16: All customer data in this workbook is SYNTHETIC, generated for illustrative purposes only.
A18: Legend
A19: Yellow fill | B19: Editable input / assumption
A20: Blue font | B20: Hardcoded input value
A21: Black font | B21: Formula (do not hardcode)
A22: Green font | B22: Link to another sheet

Sheet Tier_Criteria
A1: Scoring Assumptions (edit yellow cells to run new scenarios)
A3: 1. Weighted Scoring Factors
A4: Metric | B4: Weight | C4: Benchmark (= 100 score) | D4: Notes
A5: Avg Monthly Balance (AMB) | B5: 0.35 | C5: 2000000 | D5: ₹20L AMB benchmarked to HDFC Imperia entry AUM level
A6: Annual Income (Salary Credit x 12) | B6: 0.25 | C6: 3600000 | D6: ₹36L p.a. proxies mass-affluent income bracket
A7: Product Holding Breadth | B7: 0.15 | C7: 6 | D7: Max of 6 tracked products (SB, FD, CC, Loan, Insurance, MF)
A8: Digital Engagement Score | B8: 0.1 | C8: 100 | D8: Already scored 0-100 in Customer_Data; benchmark = ceiling
A9: Credit Card Monthly Spend | B9: 0.15 | C9: 150000 | D9: ₹1.5L/month spend benchmarked to super-premium card tier
A10: Total Weight (must equal 100%) | B10: =SUM(B5:B9) -> 1
A13: 2. Wealth Tier Thresholds (Weighted Score out of 100)
A14: Tier | B14: Min Score | C14: Max Score | D14: Notes
A15: Mass | B15: 0 | C15: 39.99 | D15: Standard retail banking coverage
A16: Mass Affluent | B16: 40 | C16: 64.99 | D16: Priority banking / entry-level RM coverage
A17: HNI | B17: 65 | C17: 84.99 | D17: Dedicated Relationship Manager, wealth product access
A18: UHNI | B18: 85 | C18: 100 | D18: Private banking desk, bespoke portfolio & AIF access

Sheet Customer_Data
A1: Customer_Data — Synthetic Retail Banking CRM Extract (n = 80)
A3: Customer_ID | B3: Age | C3: Occupation | D3: City_Tier | E3: Tenure_Years | F3: Avg_Monthly_Balance (₹) | G3: Annual_Salary_Credit (₹) | H3: Num_Existing_Products | I3: Has_Investment_Product (Y/N) | J3: Digital_Engagement_Score (0-100) | K3: Credit_Card_Spend_Monthly (₹)
A4: CUST-1001 | B4: 27 | C4: Business Owner | D4: Metro | E4: 13.5 | F4: 1870754 | G4: 1609117 | H4: 1 | I4: N | J4: 29 | K4: 45416
A5: CUST-1002 | B5: 61 | C5: Professional | D5: Metro | E5: 4 | F5: 3484524 | G5: 1293485 | H5: 4 | I5: Y | J5: 52 | K5: 63945
A6: CUST-1003 | B6: 32 | C6: Retired | D6: Tier 1 | E6: 2.1 | F6: 620338 | G6: 0 | H6: 1 | I6: N | J6: 37 | K6: 15425
A7: CUST-1004 | B7: 65 | C7: Professional | D7: Tier 1 | E7: 16 | F7: 2969312 | G7: 2877620 | H7: 4 | I7: N | J7: 47 | K7: 77088
A8: CUST-1005 | B8: 36 | C8: Retired | D8: Tier 1 | E8: 7 | F8: 980754 | G8: 0 | H8: 1 | I8: N | J8: 23 | K8: 39252
A9: CUST-1006 | B9: 40 | C9: Business Owner | D9: Tier 2 | E9: 12.5 | F9: 3132626 | G9: 2406085 | H9: 4 | I9: N | J9: 81 | K9: 101303
A10: CUST-1007 | B10: 51 | C10: Business Owner | D10: Tier 1 | E10: 16 | F10: 3138671 | G10: 3062460 | H10: 3 | I10: Y | J10: 56 | K10: 144847
A11: CUST-1008 | B11: 57 | C11: Salaried | D11: Tier 2 | E11: 2.1 | F11: 314692 | G11: 300000 | H11: 1 | I11: N | J11: 34 | K11: 11361
A12: CUST-1009 | B12: 33 | C12: Professional | D12: Metro | E12: 12.4 | F12: 1502821 | G12: 1254286 | H12: 3 | I12: N | J12: 50 | K12: 41318
A13: CUST-1010 | B13: 58 | C13: Professional | D13: Metro | E13: 16.5 | F13: 3069908 | G13: 3063428 | H13: 4 | I13: Y | J13: 54 | K13: 56263
A14: CUST-1011 | B14: 41 | C14: Salaried | D14: Tier 1 | E14: 1.5 | F14: 2884345 | G14: 4471988 | H14: 5 | I14: Y | J14: 80 | K14: 151665
A15: CUST-1012 | B15: 64 | C15: Salaried | D15: Tier 2 | E15: 7.9 | F15: 604058 | G15: 844961 | H15: 2 | I15: N | J15: 23 | K15: 23835
... A83: CUST-1080 | B83: 55 | C83: Professional | D83: Tier 1 | E83: 11.8 | F83: 124039 | G83: 300000 | H83: 1 | I83: N | J83: 29 | K83: 5020

Sheet Segmentation_Model
A1: Segmentation_Model — Wealth Score Engine & Tier Assignment
A3: Customer_ID | B3: AMB_Score | C3: Income_Score | D3: Product_Score | E3: Digital_Score | F3: CC_Spend_Score | G3: Weighted_Wealth_Score | H3: Wealth_Tier | I3: Has_Investment_Product | J3: Cross_Sell_Priority
A4: =Customer_Data!A4 -> CUST-1001 | B4: =MIN(Customer_Data!F4/Tier_Criteria!$C$5*100,100) -> 93.5377 | C4: =MIN(Customer_Data!G4/Tier_Criteria!$C$6*100,100) -> 44.697694 | D4: =MIN(Customer_Data!H4/Tier_Criteria!$C$7*100,100) -> 16.666667 | E4: =MIN(Customer_Data!J4/Tier_Criteria!$C$8*100,100) -> 29 | F4: =MIN(Customer_Data!K4/Tier_Criteria!$C$9*100,100) -> 30.277333 | G4: =B4*Tier_Criteria!$B$5+C4*Tier_Criteria!$B$6+D4*Tier_Criteria!$B$7+E4*Tier_Criteria!$B$8+F4*Tier_Criteria!$B$9 -> 53.854219 | H4: =INDEX(Tier_Criteria!$A$15:$A$18,MATCH(G4,Tier_Criteria!$B$15:$B$18,1)) -> Mass Affluent | I4: =Customer_Data!I4 -> N | J4: =IF(AND(OR(H4="HNI",H4="UHNI"),I4="N"),"High Priority - No Investment Product",IF(AND(H4="Mass Affluent",I4="N"),"Medium Priority - Entry Wealth Product","Standard / Retain")) -> Medium Priority - Entry Wealth Product
A5: =Customer_Data!A5 -> CUST-1002 | B5: =MIN(Customer_Data!F5/Tier_Criteria!$C$5*100,100) -> 100 | C5: =MIN(Customer_Data!G5/Tier_Criteria!$C$6*100,100) -> 35.930139 | D5: =MIN(Customer_Data!H5/Tier_Criteria!$C$7*100,100) -> 66.666667 | E5: =MIN(Customer_Data!J5/Tier_Criteria!$C$8*100,100) -> 52 | F5: =MIN(Customer_Data!K5/Tier_Criteria!$C$9*100,100) -> 42.63 | G5: =B5*Tier_Criteria!$B$5+C5*Tier_Criteria!$B$6+D5*Tier_Criteria!$B$7+E5*Tier_Criteria!$B$8+F5*Tier_Criteria!$B$9 -> 65.577035 | H5: =INDEX(Tier_Criteria!$A$15:$A$18,MATCH(G5,Tier_Criteria!$B$15:$B$18,1)) -> HNI | I5: =Customer_Data!I5 -> Y | J5: =IF(AND(OR(H5="HNI",H5="UHNI"),I5="N"),"High Priority - No Investment Product",IF(AND(H5="Mass Affluent",I5="N"),"Medium Priority - Entry Wealth Product","Standard / Retain")) -> Standard / Retain
A6: =Customer_Data!A6 -> CUST-1003 | B6: =MIN(Customer_Data!F6/Tier_Criteria!$C$5*100,100) -> 31.0169 | C6: =MIN(Customer_Data!G6/Tier_Criteria!$C$6*100,100) -> 0 | D6: =MIN(Customer_Data!H6/Tier_Criteria!$C$7*100,100) -> 16.666667 | E6: =MIN(Customer_Data!J6/Tier_Criteria!$C$8*100,100) -> 37 | F6: =MIN(Customer_Data!K6/Tier_Criteria!$C$9*100,100) -> 10.283333 | G6: =B6*Tier_Criteria!$B$5+C6*Tier_Criteria!$B$6+D6*Tier_Criteria!$B$7+E6*Tier_Criteria!$B$8+F6*Tier_Criteria!$B$9 -> 18.598415 | H6: =INDEX(Tier_Criteria!$A$15:$A$18,MATCH(G6,Tier_Criteria!$B$15:$B$18,1)) -> Mass | I6: =Customer_Data!I6 -> N | J6: =IF(AND(OR(H6="HNI",H6="UHNI"),I6="N"),"High Priority - No Investment Product",IF(AND(H6="Mass Affluent",I6="N"),"Medium Priority - Entry Wealth Product","Standard / Retain")) -> Standard / Retain
A7: =Customer_Data!A7 -> CUST-1004 | B7: =MIN(Customer_Data!F7/Tier_Criteria!$C$5*100,100) -> 100 | C7: =MIN(Customer_Data!G7/Tier_Criteria!$C$6*100,100) -> 79.933889 | D7: =MIN(Customer_Data!H7/Tier_Criteria!$C$7*100,100) -> 66.666667 | E7: =MIN(Customer_Data!J7/Tier_Criteria!$C$8*100,100) -> 47 | F7: =MIN(Customer_Data!K7/Tier_Criteria!$C$9*100,100) -> 51.392 | G7: =B7*Tier_Criteria!$B$5+C7*Tier_Criteria!$B$6+D7*Tier_Criteria!$B$7+E7*Tier_Criteria!$B$8+F7*Tier_Criteria!$B$9 -> 77.392272 | H7: =INDEX(Tier_Criteria!$A$15:$A$18,MATCH(G7,Tier_Criteria!$B$15:$B$18,1)) -> HNI | I7: =Customer_Data!I7 -> N | J7: =IF(AND(OR(H7="HNI",H7="UHNI"),I7="N"),"High Priority - No Investment Product",IF(AND(H7="Mass Affluent",I7="N"),"Medium Priority - Entry Wealth Product","Standard / Retain")) -> High Priority - No Investment Product
A8: =Customer_Data!A8 -> CUST-1005 | B8: =MIN(Customer_Data!F8/Tier_Criteria!$C$5*100,100) -> 49.0377 | C8: =MIN(Customer_Data!G8/Tier_Criteria!$C$6*100,100) -> 0 | D8: =MIN(Customer_Data!H8/Tier_Criteria!$C$7*100,100) -> 16.666667 | E8: =MIN(Customer_Data!J8/Tier_Criteria!$C$8*100,100) -> 23 | F8: =MIN(Customer_Data!K8/Tier_Criteria!$C$9*100,100) -> 26.168 | G8: =B8*Tier_Criteria!$B$5+C8*Tier_Criteria!$B$6+D8*Tier_Criteria!$B$7+E8*Tier_Criteria!$B$8+F8*Tier_Criteria!$B$9 -> 25.888395 | H8: =INDEX(Tier_Criteria!$A$15:$A$18,MATCH(G8,Tier_Criteria!$B$15:$B$18,1)) -> Mass | I8: =Customer_Data!I8 -> N | J8: =IF(AND(OR(H8="HNI",H8="UHNI"),I8="N"),"High Priority - No Investment Product",IF(AND(H8="Mass Affluent",I8="N"),"Medium Priority - Entry Wealth Product","Standard / Retain")) -> Standard / Retain
A9: =Customer_Data!A9 -> CUST-1006 | B9: =MIN(Customer_Data!F9/Tier_Criteria!$C$5*100,100) -> 100 | C9: =MIN(Customer_Data!G9/Tier_Criteria!$C$6*100,100) -> 66.835694 | D9: =MIN(Customer_Data!H9/Tier_Criteria!$C$7*100,100) -> 66.666667 | E9: =MIN(Customer_Data!J9/Tier_Criteria!$C$8*100,100) -> 81 | F9: =MIN(Customer_Data!K9/Tier_Criteria!$C$9*100,100) -> 67.535333 | G9: =B9*Tier_Criteria!$B$5+C9*Tier_Criteria!$B$6+D9*Tier_Criteria!$B$7+E9*Tier_Criteria!$B$8+F9*Tier_Criteria!$B$9 -> 79.939224 | H9: =INDEX(Tier_Criteria!$A$15:$A$18,MATCH(G9,Tier_Criteria!$B$15:$B$18,1)) -> HNI | I9: =Customer_Data!I9 -> N | J9: =IF(AND(OR(H9="HNI",H9="UHNI"),I9="N"),"High Priority - No Investment Product",IF(AND(H9="Mass Affluent",I9="N"),"Medium Priority - Entry Wealth Product","Standard / Retain")) -> High Priority - No Investment Product
A10: =Customer_Data!A10 -> CUST-1007 | B10: =MIN(Customer_Data!F10/Tier_Criteria!$C$5*100,100) -> 100 | C10: =MIN(Customer_Data!G10/Tier_Criteria!$C$6*100,100) -> 85.068333 | D10: =MIN(Customer_Data!H10/Tier_Criteria!$C$7*100,100) -> 50 | E10: =MIN(Customer_Data!J10/Tier_Criteria!$C$8*100,100) -> 56 | F10: =MIN(Customer_Data!K10/Tier_Criteria!$C$9*100,100) -> 96.564667 | G10: =B10*Tier_Criteria!$B$5+C10*Tier_Criteria!$B$6+D10*Tier_Criteria!$B$7+E10*Tier_Criteria!$B$8+F10*Tier_Criteria!$B$9 -> 83.851783 | H10: =INDEX(Tier_Criteria!$A$15:$A$18,MATCH(G10,Tier_Criteria!$B$15:$B$18,1)) -> HNI | I10: =Customer_Data!I10 -> Y | J10: =IF(AND(OR(H10="HNI",H10="UHNI"),I10="N"),"High Priority - No Investment Product",IF(AND(H10="Mass Affluent",I10="N"),"Medium Priority - Entry Wealth Product","Standard / Retain")) -> Standard / Retain
A11: =Customer_Data!A11 -> CUST-1008 | B11: =MIN(Customer_Data!F11/Tier_Criteria!$C$5*100,100) -> 15.7346 | C11: =MIN(Customer_Data!G11/Tier_Criteria!$C$6*100,100) -> 8.3333333 | D11: =MIN(Customer_Data!H11/Tier_Criteria!$C$7*100,100) -> 16.666667 | E11: =MIN(Customer_Data!J11/Tier_Criteria!$C$8*100,100) -> 34 | F11: =MIN(Customer_Data!K11/Tier_Criteria!$C$9*100,100) -> 7.574 | G11: =B11*Tier_Criteria!$B$5+C11*Tier_Criteria!$B$6+D11*Tier_Criteria!$B$7+E11*Tier_Criteria!$B$8+F11*Tier_Criteria!$B$9 -> 14.626543 | H11: =INDEX(Tier_Criteria!$A$15:$A$18,MATCH(G11,Tier_Criteria!$B$15:$B$18,1)) -> Mass | I11: =Customer_Data!I11 -> N | J11: =IF(AND(OR(H11="HNI",H11="UHNI"),I11="N"),"High Priority - No Investment Product",IF(AND(H11="Mass Affluent",I11="N"),"Medium Priority - Entry Wealth Product","Standard / Retain")) -> Standard / Retain
A12: =Customer_Data!A12 -> CUST-1009 | B12: =MIN(Customer_Data!F12/Tier_Criteria!$C$5*100,100) -> 75.14105 | C12: =MIN(Customer_Data!G12/Tier_Criteria!$C$6*100,100) -> 34.841278 | D12: =MIN(Customer_Data!H12/Tier_Criteria!$C$7*100,100) -> 50 | E12: =MIN(Customer_Data!J12/Tier_Criteria!$C$8*100,100) -> 50 | F12: =MIN(Customer_Data!K12/Tier_Criteria!$C$9*100,100) -> 27.545333 | G12: =B12*Tier_Criteria!$B$5+C12*Tier_Criteria!$B$6+D12*Tier_Criteria!$B$7+E12*Tier_Criteria!$B$8+F12*Tier_Criteria!$B$9 -> 51.641487 | H12: =INDEX(Tier_Criteria!$A$15:$A$18,MATCH(G12,Tier_Criteria!$B$15:$B$18,1)) -> Mass Affluent | I12: =Customer_Data!I12 -> N | J12: =IF(AND(OR(H12="HNI",H12="UHNI"),I12="N"),"High Priority - No Investment Product",IF(AND(H12="Mass Affluent",I12="N"),"Medium Priority - Entry Wealth Product","Standard / Retain")) -> Medium Priority - Entry Wealth Product
A13: =Customer_Data!A13 -> CUST-1010 | B13: =MIN(Customer_Data!F13/Tier_Criteria!$C$5*100,100) -> 100 | C13: =MIN(Customer_Data!G13/Tier_Criteria!$C$6*100,100) -> 85.095222 | D13: =MIN(Customer_Data!H13/Tier_Criteria!$C$7*100,100) -> 66.666667 | E13: =MIN(Customer_Data!J13/Tier_Criteria!$C$8*100,100) -> 54 | F13: =MIN(Customer_Data!K13/Tier_Criteria!$C$9*100,100) -> 37.508667 | G13: =B13*Tier_Criteria!$B$5+C13*Tier_Criteria!$B$6+D13*Tier_Criteria!$B$7+E13*Tier_Criteria!$B$8+F13*Tier_Criteria!$B$9 -> 77.300106 | H13: =INDEX(Tier_Criteria!$A$15:$A$18,MATCH(G13,Tier_Criteria!$B$15:$B$18,1)) -> HNI | I13: =Customer_Data!I13 -> Y | J13: =IF(AND(OR(H13="HNI",H13="UHNI"),I13="N"),"High Priority - No Investment Product",IF(AND(H13="Mass Affluent",I13="N"),"Medium Priority - Entry Wealth Product","Standard / Retain")) -> Standard / Retain
A14: =Customer_Data!A14 -> CUST-1011 | B14: =MIN(Customer_Data!F14/Tier_Criteria!$C$5*100,100) -> 100 | C14: =MIN(Customer_Data!G14/Tier_Criteria!$C$6*100,100) -> 100 | D14: =MIN(Customer_Data!H14/Tier_Criteria!$C$7*100,100) -> 83.333333 | E14: =MIN(Customer_Data!J14/Tier_Criteria!$C$8*100,100) -> 80 | F14: =MIN(Customer_Data!K14/Tier_Criteria!$C$9*100,100) -> 100 | G14: =B14*Tier_Criteria!$B$5+C14*Tier_Criteria!$B$6+D14*Tier_Criteria!$B$7+E14*Tier_Criteria!$B$8+F14*Tier_Criteria!$B$9 -> 95.5 | H14: =INDEX(Tier_Criteria!$A$15:$A$18,MATCH(G14,Tier_Criteria!$B$15:$B$18,1)) -> UHNI | I14: =Customer_Data!I14 -> Y | J14: =IF(AND(OR(H14="HNI",H14="UHNI"),I14="N"),"High Priority - No Investment Product",IF(AND(H14="Mass Affluent",I14="N"),"Medium Priority - Entry Wealth Product","Standard / Retain")) -> Standard / Retain
A15: =Customer_Data!A15 -> CUST-1012 | B15: =MIN(Customer_Data!F15/Tier_Criteria!$C$5*100,100) -> 30.2029 | C15: =MIN(Customer_Data!G15/Tier_Criteria!$C$6*100,100) -> 23.471139 | D15: =MIN(Customer_Data!H15/Tier_Criteria!$C$7*100,100) -> 33.333333 | E15: =MIN(Customer_Data!J15/Tier_Criteria!$C$8*100,100) -> 23 | F15: =MIN(Customer_Data!K15/Tier_Criteria!$C$9*100,100) -> 15.89 | G15: =B15*Tier_Criteria!$B$5+C15*Tier_Criteria!$B$6+D15*Tier_Criteria!$B$7+E15*Tier_Criteria!$B$8+F15*Tier_Criteria!$B$9 -> 26.1223 | H15: =INDEX(Tier_Criteria!$A$15:$A$18,MATCH(G15,Tier_Criteria!$B$15:$B$18,1)) -> Mass | I15: =Customer_Data!I15 -> N | J15: =IF(AND(OR(H15="HNI",H15="UHNI"),I15="N"),"High Priority - No Investment Product",IF(AND(H15="Mass Affluent",I15="N"),"Medium Priority - Entry Wealth Product","Standard / Retain")) -> Standard / Retain
... A83: =Customer_Data!A83 -> CUST-1080 | B83: =MIN(Customer_Data!F83/Tier_Criteria!$C$5*100,100) -> 6.20195 | C83: =MIN(Customer_Data!G83/Tier_Criteria!$C$6*100,100) -> 8.3333333 | D83: =MIN(Customer_Data!H83/Tier_Criteria!$C$7*100,100) -> 16.666667 | E83: =MIN(Customer_Data!J83/Tier_Criteria!$C$8*100,100) -> 29 | F83: =MIN(Customer_Data!K83/Tier_Criteria!$C$9*100,100) -> 3.3466667 | G83: =B83*Tier_Criteria!$B$5+C83*Tier_Criteria!$B$6+D83*Tier_Criteria!$B$7+E83*Tier_Criteria!$B$8+F83*Tier_Criteria!$B$9 -> 10.156016 | H83: =INDEX(Tier_Criteria!$A$15:$A$18,MATCH(G83,Tier_Criteria!$B$15:$B$18,1)) -> Mass | I83: =Customer_Data!I83 -> N | J83: =IF(AND(OR(H83="HNI",H83="UHNI"),I83="N"),"High Priority - No Investment Product",IF(AND(H83="Mass Affluent",I83="N"),"Medium Priority - Entry Wealth Product","Standard / Retain")) -> Standard / Retain

Sheet Dashboard
A1: Dashboard — Tier Distribution, AUM Concentration & Cross-Sell Priority
A3: 1. Tier Distribution
A4: Tier | B4: Customer Count | C4: % of Base | D4: Total AMB (₹) | E4: Avg AMB (₹)
A5: Mass | B5: =COUNTIF(Segmentation_Model!$H$4:$H$83,A5) -> 32 | C5: =B5/SUM($B$5:$B$8) -> 0.4 | D5: =SUMIF(Segmentation_Model!$H$4:$H$83,A5,Customer_Data!$F$4:$F$83) -> 23059531 | E5: =IFERROR(D5/B5,0) -> 720610.34
A6: Mass Affluent | B6: =COUNTIF(Segmentation_Model!$H$4:$H$83,A6) -> 28 | C6: =B6/SUM($B$5:$B$8) -> 0.35 | D6: =SUMIF(Segmentation_Model!$H$4:$H$83,A6,Customer_Data!$F$4:$F$83) -> 53189240 | E6: =IFERROR(D6/B6,0) -> 1899615.7
A7: HNI | B7: =COUNTIF(Segmentation_Model!$H$4:$H$83,A7) -> 18 | C7: =B7/SUM($B$5:$B$8) -> 0.225 | D7: =SUMIF(Segmentation_Model!$H$4:$H$83,A7,Customer_Data!$F$4:$F$83) -> 50238456 | E7: =IFERROR(D7/B7,0) -> 2791025.3
A8: UHNI | B8: =COUNTIF(Segmentation_Model!$H$4:$H$83,A8) -> 2 | C8: =B8/SUM($B$5:$B$8) -> 0.025 | D8: =SUMIF(Segmentation_Model!$H$4:$H$83,A8,Customer_Data!$F$4:$F$83) -> 6863247 | E8: =IFERROR(D8/B8,0) -> 3431623.5
A10: Total | B10: =SUM(B5:B8) -> 80 | D10: =SUM(D5:D8) -> 133350474
A13: 2. Cross-Sell Priority Flags (RM Handoff Queue)
A14: Priority Flag | B14: Customer Count
A15: High Priority - No Investment Product | B15: =COUNTIF(Segmentation_Model!$J$4:$J$83,A15) -> 4
A16: Medium Priority - Entry Wealth Product | B16: =COUNTIF(Segmentation_Model!$J$4:$J$83,A16) -> 26
A17: Standard / Retain | B17: =COUNTIF(Segmentation_Model!$J$4:$J$83,A17) -> 50
A20: 3. Key Takeaway (auto-generated)
A21: =CONCATENATE("Of ",B10," customers, ",B15," are HNI/UHNI with zero investment product penetration — ",TEXT(B15/B10,"0.0%")," of the base represents immediate cross-sell revenue at risk of attrition to a competing wealth platform.") -> Of 80 customers, 4 are HNI/UHNI with zero investment product penetration — 5.0% of the base represents immediate cross-sell revenue at risk of attrition to a competing wealth platform.
